{ "frames": [
   {
    "filename": "slime-red-american-football-hit 0.aseprite",
    "frame": { "x": 0, "y": 0, "w": 64, "h": 64 },
    "rotated": false,
    "trimmed": false,
    "spriteSourceSize": { "x": 0, "y": 0, "w": 64, "h": 64 },
    "sourceSize": { "w": 64, "h": 64 },
    "duration": 180
   },
   {
    "filename": "slime-red-american-football-hit 1.aseprite",
    "frame": { "x": 64, "y": 0, "w": 64, "h": 64 },
    "rotated": false,
    "trimmed": false,
    "spriteSourceSize": { "x": 0, "y": 0, "w": 64, "h": 64 },
    "sourceSize": { "w": 64, "h": 64 },
    "duration": 80
   },
   {
    "filename": "slime-red-american-football-hit 2.aseprite",
    "frame": { "x": 128, "y": 0, "w": 64, "h": 64 },
    "rotated": false,
    "trimmed": false,
    "spriteSourceSize": { "x": 0, "y": 0, "w": 64, "h": 64 },
    "sourceSize": { "w": 64, "h": 64 },
    "duration": 70
   },
   {
    "filename": "slime-red-american-football-hit 3.aseprite",
    "frame": { "x": 192, "y": 0, "w": 64, "h": 64 },
    "rotated": false,
    "trimmed": false,
    "spriteSourceSize": { "x": 0, "y": 0, "w": 64, "h": 64 },
    "sourceSize": { "w": 64, "h": 64 },
    "duration": 70
   },
   {
    "filename": "slime-red-american-football-hit 4.aseprite",
    "frame": { "x": 256, "y": 0, "w": 64, "h": 64 },
    "rotated": false,
    "trimmed": false,
    "spriteSourceSize": { "x": 0, "y": 0, "w": 64, "h": 64 },
    "sourceSize": { "w": 64, "h": 64 },
    "duration": 80
   },
   {
    "filename": "slime-red-american-football-hit 5.aseprite",
    "frame": { "x": 320, "y": 0, "w": 64, "h": 64 },
    "rotated": false,
    "trimmed": false,
    "spriteSourceSize": { "x": 0, "y": 0, "w": 64, "h": 64 },
    "sourceSize": { "w": 64, "h": 64 },
    "duration": 90
   },
   {
    "filename": "slime-red-american-football-hit 6.aseprite",
    "frame": { "x": 0, "y": 64, "w": 64, "h": 64 },
    "rotated": false,
    "trimmed": false,
    "spriteSourceSize": { "x": 0, "y": 0, "w": 64, "h": 64 },
    "sourceSize": { "w": 64, "h": 64 },
    "duration": 90
   },
   {
    "filename": "slime-red-american-football-hit 7.aseprite",
    "frame": { "x": 64, "y": 64, "w": 64, "h": 64 },
    "rotated": false,
    "trimmed": false,
    "spriteSourceSize": { "x": 0, "y": 0, "w": 64, "h": 64 },
    "sourceSize": { "w": 64, "h": 64 },
    "duration": 90
   },
   {
    "filename": "slime-red-american-football-hit 8.aseprite",
    "frame": { "x": 128, "y": 64, "w": 64, "h": 64 },
    "rotated": false,
    "trimmed": false,
    "spriteSourceSize": { "x": 0, "y": 0, "w": 64, "h": 64 },
    "sourceSize": { "w": 64, "h": 64 },
    "duration": 100
   },
   {
    "filename": "slime-red-american-football-hit 9.aseprite",
    "frame": { "x": 192, "y": 64, "w": 64, "h": 64 },
    "rotated": false,
    "trimmed": false,
    "spriteSourceSize": { "x": 0, "y": 0, "w": 64, "h": 64 },
    "sourceSize": { "w": 64, "h": 64 },
    "duration": 90
   },
   {
    "filename": "slime-red-american-football-hit 10.aseprite",
    "frame": { "x": 256, "y": 64, "w": 64, "h": 64 },
    "rotated": false,
    "trimmed": false,
    "spriteSourceSize": { "x": 0, "y": 0, "w": 64, "h": 64 },
    "sourceSize": { "w": 64, "h": 64 },
    "duration": 90
   },
   {
    "filename": "slime-red-american-football-hit 11.aseprite",
    "frame": { "x": 320, "y": 64, "w": 64, "h": 64 },
    "rotated": false,
    "trimmed": false,
    "spriteSourceSize": { "x": 0, "y": 0, "w": 64, "h": 64 },
    "sourceSize": { "w": 64, "h": 64 },
    "duration": 100
   },
   {
    "filename": "slime-red-american-football-hit 12.aseprite",
    "frame": { "x": 0, "y": 128, "w": 64, "h": 64 },
    "rotated": false,
    "trimmed": false,
    "spriteSourceSize": { "x": 0, "y": 0, "w": 64, "h": 64 },
    "sourceSize": { "w": 64, "h": 64 },
    "duration": 110
   },
   {
    "filename": "slime-red-american-football-hit 13.aseprite",
    "frame": { "x": 64, "y": 128, "w": 64, "h": 64 },
    "rotated": false,
    "trimmed": false,
    "spriteSourceSize": { "x": 0, "y": 0, "w": 64, "h": 64 },
    "sourceSize": { "w": 64, "h": 64 },
    "duration": 110
   },
   {
    "filename": "slime-red-american-football-hit 14.aseprite",
    "frame": { "x": 128, "y": 128, "w": 64, "h": 64 },
    "rotated": false,
    "trimmed": false,
    "spriteSourceSize": { "x": 0, "y": 0, "w": 64, "h": 64 },
    "sourceSize": { "w": 64, "h": 64 },
    "duration": 120
   },
   {
    "filename": "slime-red-american-football-hit 15.aseprite",
    "frame": { "x": 192, "y": 128, "w": 64, "h": 64 },
    "rotated": false,
    "trimmed": false,
    "spriteSourceSize": { "x": 0, "y": 0, "w": 64, "h": 64 },
    "sourceSize": { "w": 64, "h": 64 },
    "duration": 150
   },
   {
    "filename": "slime-red-american-football-hit 16.aseprite",
    "frame": { "x": 256, "y": 128, "w": 64, "h": 64 },
    "rotated": false,
    "trimmed": false,
    "spriteSourceSize": { "x": 0, "y": 0, "w": 64, "h": 64 },
    "sourceSize": { "w": 64, "h": 64 },
    "duration": 180
   },
   {
    "filename": "slime-red-american-football-hit 17.aseprite",
    "frame": { "x": 320, "y": 128, "w": 64, "h": 64 },
    "rotated": false,
    "trimmed": false,
    "spriteSourceSize": { "x": 0, "y": 0, "w": 64, "h": 64 },
    "sourceSize": { "w": 64, "h": 64 },
    "duration": 240
   }
 ],
 "meta": {
  "app": "https://www.aseprite.org/",
  "version": "1.x-dev",
  "image": "slime-red-american-football-hit-sheet.png",
  "format": "RGBA8888",
  "size": { "w": 384, "h": 192 },
  "scale": "1",
  "frameTags": [
   { "name": "american_football_hit", "from": 0, "to": 17, "direction": "forward", "color": "#000000ff" }
  ],
  "layers": [
   { "name": "slime", "opacity": 255, "blendMode": "normal" },
   { "name": "american_football", "opacity": 255, "blendMode": "normal" }
  ]
 }
}
